GameMaker/Assets.py
GameMaker/Globals.py
GameMaker/Helper.py
GameMaker/Physics.py
GameMaker/__init__.py
GameMaker/examples/Demo_Button.py
GameMaker/examples/Demo_Collisions.py
GameMaker/examples/Demo_Gravity.py
GameMaker/examples/Demo_Image.py
GameMaker/examples/Demo_ImageList.py
GameMaker/examples/Demo_ProgressBar.py
GameMaker/examples/Demo_Text.py
GameMaker/examples/Demo_Textbox.py
GameMaker/examples/Demo_Window.py
GameMaker-0.1.4.dist-info/LICENSE
GameMaker-0.1.4.dist-info/METADATA
GameMaker-0.1.4.dist-info/WHEEL
GameMaker-0.1.4.dist-info/top_level.txt
GameMaker-0.1.4.dist-info/RECORD
